npc/vsrc/top.v
module top(
	input	wire [1:0] x0,
	input	wire [1:0] x1,
	input	wire [1:0] x2,
	input	wire [1:0] x3,
	input	wire [1:0] Y,
	output	reg  [1:0] F
);

always@(*)
	case (Y) 
		2'b00: F = x0;
		2'b01: F = x1;
		2'b10: F = x2;
		2'b11: F = x3;
	default: F = 2'b00;
	endcase


endmodule

npc/dump.vcd
$version Generated by VerilatedVcd $end
$timescale 1s $end

 $scope module TOP $end
  $var wire  2 ( F [1:0] $end
  $var wire  2 ' Y [1:0] $end
  $var wire  2 # x0 [1:0] $end
  $var wire  2 $ x1 [1:0] $end
  $var wire  2 % x2 [1:0] $end
  $var wire  2 & x3 [1:0] $end
  $scope module top $end
   $var wire  2 ( F [1:0] $end
   $var wire  2 ' Y [1:0] $end
   $var wire  2 # x0 [1:0] $end
   $var wire  2 $ x1 [1:0] $end
   $var wire  2 % x2 [1:0] $end
   $var wire  2 & x3 [1:0] $end
  $upscope $end
 $upscope $end
$enddefinitions $end


#1
b01 #
b00 $
b00 %
b00 &
b00 '
b01 (
#2
b00 #
b01 $
b00 (
#3
b01 #
b01 (
#4
b00 #
b00 $
b01 %
b00 (
#5
b01 #
b01 (
#6
b00 #
b01 $
b00 (
#7
b01 #
b01 (
#8
b00 #
b00 $
b00 %
b01 &
b00 (
#9
b01 #
b01 (
#10
b00 #
b01 $
b00 (
#11
b01 #
b01 (
#12
b00 #
b00 $
b01 %
b00 (
#13
b01 #
b01 (
#14
b00 #
b01 $
b00 (
#15
b01 #
b01 (
#16
b00 #
b00 $
b00 %
b00 &
b00 (
#17
b01 #
b01 '
#18
b00 #
b01 $
b01 (
#19
b01 #
#20
b00 #
b00 $
b01 %
b00 (
#21
b01 #
#22
b00 #
b01 $
b01 (
#23
b01 #
#24
b00 #
b00 $
b00 %
b01 &
b00 (
#25
b01 #
#26
b00 #
b01 $
b01 (
#27
b01 #
#28
b00 #
b00 $
b01 %
b00 (
#29
b01 #
#30
b00 #
b01 $
b01 (
#31
b01 #
#32
b00 #
b00 $
b00 %
b00 &
b00 (
#33
b01 #
b10 '
#34
b00 #
b01 $
#35
b01 #
#36
b00 #
b00 $
b01 %
b01 (
#37
b01 #
#38
b00 #
b01 $
#39
b01 #
#40
b00 #
b00 $
b00 %
b01 &
b00 (
#41
b01 #
#42
b00 #
b01 $
#43
b01 #
#44
b00 #
b00 $
b01 %
b01 (
#45
b01 #
#46
b00 #
b01 $
#47
b01 #
#48
b00 #
b00 $
b00 %
b00 &
b00 (
#49
b01 #
b11 '
#50
b00 #
b01 $
#51
b01 #
#52
b00 #
b00 $
b01 %
#53
b01 #
#54
b00 #
b01 $
#55
b01 #
#56
b00 #
b00 $
b00 %
b01 &
b01 (
#57
b01 #
#58
b00 #
b01 $
#59
b01 #
#60
b00 #
b00 $
b01 %
#61
b01 #
#62
b00 #
b01 $
#63
b01 #
#64
b00 #
b00 $
b00 %
b00 &
b00 (
#65
b00 '
