npc/vsrc/mux2bit41.v
module mux2bit41(
	input	wire [1:0] x0,
	input	wire [1:0] x1,
	input	wire [1:0] x2,
	input	wire [1:0] x3,
	input	wire [1:0] Y,
	output	reg  [1:0] F
);

always@(*)
	case (Y) 
		2'b00: F = x0;
		2'b01: F = x1;
		2'b10: F = x2;
		2'b11: F = x3;
	default: F = 2'b00;
	endcase


endmodule

npc/dump.vcd
$version Generated by VerilatedVcd $end
$timescale 1s $end

 $scope module TOP $end
  $var wire  2 ( F [1:0] $end
  $var wire  2 ' Y [1:0] $end
  $var wire  2 # x0 [1:0] $end
  $var wire  2 $ x1 [1:0] $end
  $var wire  2 % x2 [1:0] $end
  $var wire  2 & x3 [1:0] $end
  $scope module mux2bit41 $end
   $var wire  2 ( F [1:0] $end
   $var wire  2 ' Y [1:0] $end
   $var wire  2 # x0 [1:0] $end
   $var wire  2 $ x1 [1:0] $end
   $var wire  2 % x2 [1:0] $end
   $var wire  2 & x3 [1:0] $end
  $upscope $end
 $upscope $end
$enddefinitions $end


#1
b00 #
b00 $
b00 %
b00 &
b00 '
b00 (
#2
b01 #
b01 (
#3
b00 #
b01 $
b00 (
#4
b01 #
b01 (
#5
b00 #
b00 $
b01 %
b00 (
#6
b01 #
b01 (
#7
b00 #
b01 $
b00 (
#8
b01 #
b01 (
#9
b00 #
b00 $
b00 %
b01 &
b00 (
#10
b01 #
b01 (
#11
b00 #
b01 $
b00 (
#12
b01 #
b01 (
#13
b00 #
b00 $
b01 %
b00 (
#14
b01 #
b01 (
#15
b00 #
b01 $
b00 (
#16
b01 #
b01 (
#17
b00 #
b00 $
b00 %
b00 &
b01 '
b00 (
#18
b01 #
#19
b00 #
b01 $
b01 (
#20
b01 #
#21
b00 #
b00 $
b01 %
b00 (
#22
b01 #
#23
b00 #
b01 $
b01 (
#24
b01 #
#25
b00 #
b00 $
b00 %
b01 &
b00 (
#26
b01 #
#27
b00 #
b01 $
b01 (
#28
b01 #
#29
b00 #
b00 $
b01 %
b00 (
#30
b01 #
#31
b00 #
b01 $
b01 (
#32
b01 #
#33
b00 #
b00 $
b00 %
b00 &
b10 '
b00 (
#34
b01 #
#35
b00 #
b01 $
#36
b01 #
#37
b00 #
b00 $
b01 %
b01 (
#38
b01 #
#39
b00 #
b01 $
#40
b01 #
#41
b00 #
b00 $
b00 %
b01 &
b00 (
#42
b01 #
#43
b00 #
b01 $
#44
b01 #
#45
b00 #
b00 $
b01 %
b01 (
#46
b01 #
#47
b00 #
b01 $
#48
b01 #
#49
b00 #
b00 $
b00 %
b00 &
b11 '
b00 (
#50
b01 #
#51
b00 #
b01 $
#52
b01 #
#53
b00 #
b00 $
b01 %
#54
b01 #
#55
b00 #
b01 $
#56
b01 #
#57
b00 #
b00 $
b00 %
b01 &
b01 (
#58
b01 #
#59
b00 #
b01 $
#60
b01 #
#61
b00 #
b00 $
b01 %
#62
b01 #
#63
b00 #
b01 $
#64
b01 #
#65
b00 #
b00 $
b00 %
b00 &
b00 '
b00 (
